Workbook

Sheet Datos_generales
A1: COOPERATIVA FINANCIERA EJEMPLO
A2: Datos generales del corte
A4: Fecha de corte | B4: 46265
A5: Patrimonio técnico (COP) | B5: 98200000000
A6: Elaborado por | B6: Tesorería
A7: Revisado por | B7: Área de Riesgos

Sheet Inversiones
A1: COOPERATIVA FINANCIERA EJEMPLO
A2: Portafolio de inversiones - corte 31/08/2026
A3: Cifras en pesos colombianos. Fuente: Tesorería (consolidado manual).
A5: No. | B5: Especie / Nemotécnico | C5: Tipo de instrumento | D5: Emisor | E5: Calificación | F5: Portafolio | G5: Clasificación contable | H5: Moneda | I5: Valor nominal | J5: Tasa facial | K5: Margen IBR | L5: Modalidad | M5: Periodicidad | N5: Fecha emisión | O5: Fecha vencimiento | P5: Valor de mercado | Q5: Beta | R5: Restringido
A6: 101 | B6: Cuenta de ahorros 2201 | C6: Cuenta de ahorros | D6: Banco Altiplano | E6: AAA | F6: Tesorería | G6: Disponible | H6: COP | I6: 3200000000 | P6: 3200000000 | R6: No
A7: 102 | B7: Cuenta de ahorros 4410 | C7: Cuenta de ahorros | D7: Banco Cordillera | E7: AAA | F7: Tesorería | G7: Disponible | H7: COP | I7: 6500000000 | P7: 6500000000 | R7: No
A8: 103 | B8: FIC Renta Vista | C8: FIC vista | D8: FIC Renta Vista (Fiduciaria Sabana) | E8: AAA | F8: Tesorería | G8: Disponible | H8: COP | I8: 5800000000 | P8: 5800000000 | R8: No
A9: 201 | B9: TES TF 5,75% nov-2027 | C9: TES | D9: Nación - MHCP | E9: Nación | F9: Fondo de liquidez | G9: Disponible para la venta | H9: COP | I9: 9000000000 | J9: 0.0575 | L9: EA | M9: AV | N9: 44138 | O9: 46694 | P9: 8800252524 | R9: No
A10: 202 | B10: TES TF 6,00% abr-2028 | C10: TES | D10: Nación - MHCP | E10: Nación | F10: Tesorería | G10: Negociable | H10: COP | I10: 8000000000 | J10: 0.06 | L10: EA | M10: AV | N10: 41027 | O10: 46871 | P10: 7403484583 | R10: No
A11: 203 | B11: TES TF 7,75% sep-2030 | C11: TES | D11: Nación - MHCP | E11: Nación | F11: Tesorería | G11: Negociable | H11: COP | I11: 7000000000 | J11: 0.0775 | L11: EA | M11: AV | N11: 41900 | O11: 47744 | P11: 6521809350 | R11: No
A12: 204 | B12: TES TF 7,00% mar-2031 | C12: TES | D12: Nación - MHCP | E12: Nación | F12: Tesorería | G12: Disponible para la venta | H12: COP | I12: 6000000000 | J12: 0.07 | L12: EA | M12: AV | N12: 44281 | O12: 47933 | P12: 5084372810 | R12: No
A13: 205 | B13: TES TF 7,00% jun-2032 | C13: TES | D13: Nación - MHCP | E13: Nación | F13: Tesorería | G13: Disponible para la venta | H13: COP | I13: 5000000000 | J13: 0.07 | L13: EA | M13: AV | N13: 42551 | O13: 48395 | P13: 3967742022 | R13: Sí
A14: 206 | B14: TES TF 13,25% feb-2033 | C14: TES | D14: Nación - MHCP | E14: Nación | F14: Tesorería | G14: Negociable | H14: COP | I14: 4000000000 | J14: 0.1325 | L14: EA | M14: AV | N14: 44966 | O14: 48619 | P14: 4414018115 | R14: No
A15: 207 | B15: TES TF 7,25% oct-2034 | C15: TES | D15: Nación - MHCP | E15: Nación | F15: Tesorería | G15: Negociable | H15: COP | I15: 6000000000 | J15: 0.0725 | L15: EA | M15: AV | N15: 43756 | O15: 49235 | P15: 4826801854 | R15: No
A16: 208 | B16: TES TF 6,25% jul-2036 | C16: TES | D16: Nación - MHCP | E16: Nación | F16: Tesorería | G16: Negociable | H16: COP | I16: 3000000000 | J16: 0.0625 | L16: EA | M16: AV | N16: 44386 | O16: 49865 | P16: 1999255083 | R16: No
A17: 301 | B17: CDT Banco Cordillera 10,90% TV | C17: CDT | D17: Banco Cordillera S.A. | E17: AAA | F17: Tesorería | G17: Al vencimiento | H17: COP | I17: 4500000000 | J17: 0.109 | L17: EA | M17: TV | N17: 45823 | O17: 46553 | P17: 4508236661 | R17: No
A18: 302 | B18: CDT Banco Cordillera 11,40% SV | C18: CDT | D18: BANCO CORDILLERA | E18: AAA | F18: Tesorería | G18: Disponible para la venta | H18: COP | I18: 3500000000 | J18: 0.114 | L18: EA | M18: SV | N18: 46101 | O18: 46832 | P18: 3583109717 | R18: No
A19: 303 | B19: CDT Banco Cordillera 12,10% AV | C19: CDT | D19: Bco. Cordillera | E19: AAA | F19: Tesorería | G19: Disponible para la venta | H19: COP | I19: 3000000000 | J19: 12.1 | L19: EA | M19: AV | N19: 46006 | O19: 15/12/2027 | P19: 3203770361 | R19: No
A20: 304 | B20: CDT IBR Banco Altiplano IBR+1,90% TV | C20: CDT IBR | D20: Banco Altiplano | E20: AAA | F20: Tesorería | G20: Disponible para la venta | H20: COP | I20: 4000000000 | K20: 0.019 | L20: EA | M20: TV | N20: 45910 | O20: 47006 | P20: 4172981296 | R20: No
A21: 305 | B21: CDT IBR Banco Guayacán IBR+2,60% TV | C21: CDT IBR | D21: Banco Guayacán | E21: AA+ | F21: Tesorería | G21: Disponible para la venta | H21: COP | I21: 4000000000 | K21: 0.026 | L21: EA | M21: TV | N21: 45966 | O21: 46696 | P21: 4073672643 | R21: No
A22: 306 | B22: CDT Financiera Río Claro 12,80% SV | C22: CDT | D22: Financiera Río Claro | E22: AA | F22: Tesorería | G22: Al vencimiento | H22: COP | I22: 3000000000 | J22: 0.128 | L22: EA | M22: SV | N22: 45952 | O22: 46499 | P22: 3108576152 | R22: No
A23: 307 | B23: CDT Banco Guayacán 11,90% PV | C23: CDT | D23: Banco Guayacán | E23: AA+ | F23: Tesorería | G23: Al vencimiento | H23: COP | I23: 2500000000 | J23: 0.119 | L23: EA | M23: PV | N23: 46091 | O23: 46456 | P23: 2604350268 | R23: No
A24: 308 | B24: CDT Banco Altiplano 11,60% PV | C24: CDT | D24: Banco Altiplano | E24: F1+ | F24: Tesorería | G24: Al vencimiento | H24: COP | I24: 2500000000 | J24: 0.116 | L24: EA | M24: PV | N24: 46174 | O24: 46357 | P24: 2557355341 | R24: No
A25: 309 | B25: CDT Leasing Nevado 12,40% TV | C25: CDT | D25: Leasing Nevado | E25: AA | F25: Tesorería | G25: Disponible para la venta | H25: COP | I25: 2000000000 | J25: 0.124 | L25: EA | M25: TV | N25: 45930 | O25: 46660 | P25: 1994537761 | R25: No
A26: 310 | B26: CDT Leasing Nevado 10,20% PV | C26: CDT | D26: Leasing Nevado S.A. | E26: AA | F26: Tesorería | G26: Al vencimiento | H26: COP | I26: 1500000000 | J26: 0.102 | L26: EA | M26: PV | N26: 45915 | O26: 46280 | P26: 1640159666 | R26: No
A27: 401 | B27: Bono Energía del Norte 11,50% TV 2031 | C27: Bono ordinario | D27: Energía del Norte S.A. E.S.P. | E27: AAA | F27: Tesorería | G27: Disponible para la venta | H27: COP | I27: 4000000000 | J27: 0.115 | L27: EA | M27: TV | N27: 45427 | O27: 47983 | P27: 3766678447 | R27: No
A28: 402 | B28: Bono Corporación Sabana 12,20% SV 2029 | C28: Bono ordinario | D28: Corporación Sabana | E28: AA+ | F28: Tesorería | G28: Disponible para la venta | H28: COP | I28: 3500000000 | J28: 0.122 | L28: EA | M28: SV | N28: 45534 | O28: 47360 | P28: 3346930741 | R28: No
A29: 403 | B29: Bono Constructora Ceiba 14,80% TV 2028 | C29: Bono ordinario | D29: Constructora Ceiba S.A. | E29: A+ | F29: Tesorería | G29: Disponible para la venta | H29: COP | I29: 2500000000 | J29: 0.148 | L29: EA | M29: TV | N29: 45991 | O29: 47087 | P29: 2449485764 | R29: No
A30: 501 | B30: ETF acciones Colombia | C30: ETF acciones locales | D30: ETF Índice Local | F30: Tesorería | G30: Negociable | H30: COP | I30: 1500000 | P30: 3218596770 | Q30: 1 | R30: No
A31: 601 | B31: Cuenta de compensación USD | C31: Depósito en USD | D31: Banco Guayacán | E31: AA+ | F31: Tesorería | G31: Disponible | H31: USD | I31: 950000 | P31: 3086286550 | R31: No
B33: TOTAL | I33: =SUM(I6:I31) | P33: =SUM(P6:P31)

Sheet Flujos_liquidez
A1: COOPERATIVA FINANCIERA EJEMPLO
A2: Flujos contractuales proyectados (próximos 120 días)
A4: Fecha | B4: Concepto | C4: Sentido | D4: Monto (COP)
A5: 46266 | B5: Vencimiento de CDAT | C5: Salida | D5: 2350630886
A6: 46267 | B6: Vencimiento de CDAT | C6: Salida | D6: 2133975242
A7: 46268 | B7: Vencimiento de CDAT | C7: Salida | D7: 1429540816
A8: 46268 | B8: Desembolsos de crédito comprometidos | C8: Salida | D8: 4150494278
A9: 46268 | B9: Recaudo de cartera | C9: Entrada | D9: 6450083147
A10: 46269 | B10: Vencimiento de CDAT | C10: Salida | D10: 2225333693
A11: 46272 | B11: Vencimiento de CDAT | C11: Salida | D11: 2197662108
A12: 46273 | B12: Vencimiento de CDAT | C12: Salida | D12: 1720750651
A13: 46274 | B13: Vencimiento de CDAT | C13: Salida | D13: 2064107637
A14: 46275 | B14: Vencimiento de CDAT | C14: Salida | D14: 2329382830
A15: 46275 | B15: Desembolsos de crédito comprometidos | C15: Salida | D15: 4079539192
A16: 46275 | B16: Recaudo de cartera | C16: Entrada | D16: 6645956684
... A104: 46380 | B104: Recaudo de cartera | C104: Entrada | D104: 6539066719

Sheet Depositos_vista
A1: COOPERATIVA FINANCIERA EJEMPLO
A2: Saldos de depósitos a la vista al corte
A4: Producto | B4: Saldo (COP)
A5: Ahorro a la vista | B5: 148000000000
A6: Ahorro programado | B6: 22200000000

Sheet Resumen_manual
A1: Resumen de concentración por emisor (elaborado manualmente)
A2: Tabla dinámica / SUMAR.SI sobre la columna Emisor tal como está escrita.
A3: Tiempo estimado de elaboración mensual del informe manual: 4 horas.
A5: Emisor | B5: Valor de mercado | C5: % del portafolio | D5: Límite | E5: Estado
A6: Banco Altiplano | B6: =SUMIF(Inversiones!$D$6:$D$31,A6,Inversiones!$P$6:$P$31) | C6: =IFERROR(B6/$B$21,0) | D6: 0.15 | E6: =IF(D6="N.A.","N.A.",IF(C6>D6,"EXCEDE","Cumple"))
A7: Banco Cordillera | B7: =SUMIF(Inversiones!$D$6:$D$31,A7,Inversiones!$P$6:$P$31) | C7: =IFERROR(B7/$B$21,0) | D7: 0.15 | E7: =IF(D7="N.A.","N.A.",IF(C7>D7,"EXCEDE","Cumple"))
A8: FIC Renta Vista (Fiduciaria Sabana) | B8: =SUMIF(Inversiones!$D$6:$D$31,A8,Inversiones!$P$6:$P$31) | C8: =IFERROR(B8/$B$21,0) | D8: 0.15 | E8: =IF(D8="N.A.","N.A.",IF(C8>D8,"EXCEDE","Cumple"))
A9: Nación - MHCP | B9: =SUMIF(Inversiones!$D$6:$D$31,A9,Inversiones!$P$6:$P$31) | C9: =IFERROR(B9/$B$21,0) | D9: N.A. | E9: =IF(D9="N.A.","N.A.",IF(C9>D9,"EXCEDE","Cumple"))
A10: Banco Cordillera S.A. | B10: =SUMIF(Inversiones!$D$6:$D$31,A10,Inversiones!$P$6:$P$31) | C10: =IFERROR(B10/$B$21,0) | D10: 0.15 | E10: =IF(D10="N.A.","N.A.",IF(C10>D10,"EXCEDE","Cumple"))
A11: Bco. Cordillera | B11: =SUMIF(Inversiones!$D$6:$D$31,A11,Inversiones!$P$6:$P$31) | C11: =IFERROR(B11/$B$21,0) | D11: 0.15 | E11: =IF(D11="N.A.","N.A.",IF(C11>D11,"EXCEDE","Cumple"))
A12: Banco Guayacán | B12: =SUMIF(Inversiones!$D$6:$D$31,A12,Inversiones!$P$6:$P$31) | C12: =IFERROR(B12/$B$21,0) | D12: 0.15 | E12: =IF(D12="N.A.","N.A.",IF(C12>D12,"EXCEDE","Cumple"))
A13: Financiera Río Claro | B13: =SUMIF(Inversiones!$D$6:$D$31,A13,Inversiones!$P$6:$P$31) | C13: =IFERROR(B13/$B$21,0) | D13: 0.15 | E13: =IF(D13="N.A.","N.A.",IF(C13>D13,"EXCEDE","Cumple"))
A14: Leasing Nevado | B14: =SUMIF(Inversiones!$D$6:$D$31,A14,Inversiones!$P$6:$P$31) | C14: =IFERROR(B14/$B$21,0) | D14: 0.15 | E14: =IF(D14="N.A.","N.A.",IF(C14>D14,"EXCEDE","Cumple"))
A15: Leasing Nevado S.A. | B15: =SUMIF(Inversiones!$D$6:$D$31,A15,Inversiones!$P$6:$P$31) | C15: =IFERROR(B15/$B$21,0) | D15: 0.15 | E15: =IF(D15="N.A.","N.A.",IF(C15>D15,"EXCEDE","Cumple"))
A16: Energía del Norte S.A. E.S.P. | B16: =SUMIF(Inversiones!$D$6:$D$31,A16,Inversiones!$P$6:$P$31) | C16: =IFERROR(B16/$B$21,0) | D16: 0.15 | E16: =IF(D16="N.A.","N.A.",IF(C16>D16,"EXCEDE","Cumple"))
A17: Corporación Sabana | B17: =SUMIF(Inversiones!$D$6:$D$31,A17,Inversiones!$P$6:$P$31) | C17: =IFERROR(B17/$B$21,0) | D17: 0.15 | E17: =IF(D17="N.A.","N.A.",IF(C17>D17,"EXCEDE","Cumple"))
A18: Constructora Ceiba S.A. | B18: =SUMIF(Inversiones!$D$6:$D$31,A18,Inversiones!$P$6:$P$31) | C18: =IFERROR(B18/$B$21,0) | D18: 0.15 | E18: =IF(D18="N.A.","N.A.",IF(C18>D18,"EXCEDE","Cumple"))
A19: ETF Índice Local | B19: =SUMIF(Inversiones!$D$6:$D$31,A19,Inversiones!$P$6:$P$31) | C19: =IFERROR(B19/$B$21,0) | D19: 0.15 | E19: =IF(D19="N.A.","N.A.",IF(C19>D19,"EXCEDE","Cumple"))
A21: TOTAL | B21: =SUM(B6:B19)
